<Properties StartupConfiguration="{B6987EF8-3EEE-4D5A-A6CF-64CEF3458A74}|Default">
  <MonoDevelop.Ide.Workbench ActiveDocument="CloudCoinIOS/Core/Safe.cs">
    <Files>
      <File FileName="CloudCoinIOS/ViewControllers/AuthorizationViewController.cs" Line="15" Column="51" />
      <File FileName="CloudCoinIOS/ViewControllers/EnterPassViewController.cs" Line="14" Column="49" />
      <File FileName="CloudCoinIOS/ViewControllers/MainViewController.cs" Line="110" Column="6" />
      <File FileName="CloudCoinIOS/AppDelegate.cs" Line="69" Column="13" />
      <File FileName="CloudCoinIOS/Core/Safe.cs" Line="62" Column="12" />
    </Files>
  </MonoDevelop.Ide.Workbench>
  <MonoDevelop.Ide.Workspace ActiveConfiguration="Debug|iPhone" />
  <MonoDevelop.Ide.DebuggingService.Breakpoints>
    <BreakpointStore>
      <Breakpoint file="/Volumes/Working/Xamarin/CloudCoin/iOS/CloudCoinIOS/CloudCoinIOS/ViewControllers/MainViewController.cs" relfile="CloudCoinIOS/ViewControllers/MainViewController.cs" line="79" column="1" />
    </BreakpointStore>
  </MonoDevelop.Ide.DebuggingService.Breakpoints>
  <MonoDevelop.Ide.DebuggingService.PinnedWatches />
  <MonoDevelop.Ide.ItemProperties.CloudCoinIOS PreferredExecutionTarget="MonoDevelop.IPhone.IPhoneDeviceTarget.eeef4730b8f9ecdf95c8994c3904326b713973d1" automaticSigning="False" />
  <MultiItemStartupConfigurations />
</Properties>