<Properties StartupConfiguration="{B6987EF8-3EEE-4D5A-A6CF-64CEF3458A74}|Default">
  <MonoDevelop.Ide.Workbench ActiveDocument="CloudCoinIOS/ViewControllers/ImportViewController.cs">
    <Files>
      <File FileName="CloudCoinIOS/ViewControllers/MainViewController.cs" Line="29" Column="28" />
      <File FileName="CloudCoinIOS/ViewControllers/ImportViewController.cs" Line="89" Column="22" />
      <File FileName="CloudCoinIOS/ViewControllers/FixFrackedViewController.cs" Line="60" Column="14" />
      <File FileName="CloudCoinIOS/Entitlements.plist" />
    </Files>
  </MonoDevelop.Ide.Workbench>
  <MonoDevelop.Ide.Workspace ActiveConfiguration="Debug|iPhone" />
  <MonoDevelop.Ide.DebuggingService.Breakpoints>
    <BreakpointStore />
  </MonoDevelop.Ide.DebuggingService.Breakpoints>
  <MonoDevelop.Ide.DebuggingService.PinnedWatches />
  <MonoDevelop.Ide.ItemProperties.CloudCoinIOS PreferredExecutionTarget="MonoDevelop.IPhone.IPhoneDeviceTarget.83809d35a1545f98d8d268928b43b928630fdea2" automaticSigning="False" />
  <MultiItemStartupConfigurations />
</Properties>